py_stats_toolkit/__init__.py
py_stats_toolkit/capsules/BaseCapsule.py
py_stats_toolkit/capsules/__init__.py
py_stats_toolkit/stats/__init__.py
py_stats_toolkit/utils/__init__.py
py_stats_toolkit/utils/data_transformation.py
py_stats_toolkit/utils/data_validation.py
py_stats_toolkit/utils/metrics.py
py_stats_toolkit/visualization/__init__.py
py_stats_toolkit/visualization/basic_plots.py
py_stats_toolkit/visualization/statistical_plots.py
py_stats_toolkit/visualization/time_series_plots.py
py_stats_toolkit-0.1.2.dist-info/licenses/LICENSE
py_stats_toolkit-0.1.2.dist-info/METADATA
py_stats_toolkit-0.1.2.dist-info/WHEEL
py_stats_toolkit-0.1.2.dist-info/top_level.txt
py_stats_toolkit-0.1.2.dist-info/RECORD
