Metadata-Version: 2.4
Name: py_stats_toolkit
Version: 0.1.2
Summary: Une boîte à outils complète pour l'analyse statistique en Python
Home-page: https://github.com/PhoenixGuardianTools/py-stats-toolkit
Author: Phoenix Project
Author-email: contact@phonxproject.onmicrosoft.com
Classifier: Development Status :: 3 - Alpha
Classifier: Intended Audience :: Science/Research
Classifier: License :: OSI Approved :: MIT License
Classifier: Programming Language :: Python :: 3
Classifier: Programming Language :: Python :: 3.8
Classifier: Programming Language :: Python :: 3.9
Classifier: Programming Language :: Python :: 3.10
Requires-Python: >=3.8
License-File: LICENSE
Requires-Dist: numpy>=1.20.0
Requires-Dist: pandas>=1.3.0
Requires-Dist: scikit-learn>=0.24.0
Requires-Dist: seaborn>=0.11.0
Requires-Dist: matplotlib>=3.4.0
Requires-Dist: scipy>=1.7.0
Requires-Dist: lifelines>=0.26.0
Requires-Dist: joblib>=1.0.0
Requires-Dist: statsmodels>=0.13.0
Requires-Dist: ephem>=4.1.0
Dynamic: author
Dynamic: author-email
Dynamic: classifier
Dynamic: description
Dynamic: description-content-type
Dynamic: home-page
Dynamic: license-file
Dynamic: requires-dist
Dynamic: requires-python
Dynamic: summary
